chemsolve/__init__.py
chemsolve/_release.py
chemsolve/compound.py
chemsolve/element.py
chemsolve/physics.py
chemsolve/ranking.py
chemsolve/reaction.py
chemsolve/electrochemistry/__init__.py
chemsolve/electrochemistry/ionic.py
chemsolve/electrochemistry/molar.py
chemsolve/electrochemistry/redox.py
chemsolve/gases/__init__.py
chemsolve/gases/idealgas.py
chemsolve/quantum/__init__.py
chemsolve/quantum/photoelectric.py
chemsolve/quantum/photon.py
chemsolve/solutions/__init__.py
chemsolve/solutions/molar.py
chemsolve/solutions/properties.py
chemsolve/solutions/titration.py
chemsolve/thermodynamics/__init__.py
chemsolve/thermodynamics/free_energy.py
chemsolve/utils/__init__.py
chemsolve/utils/_unicode_constants.py
chemsolve/utils/combustion.py
chemsolve/utils/constants.py
chemsolve/utils/conversion.py
chemsolve/utils/errors.py
chemsolve/utils/from_formula.py
chemsolve/utils/periodictable.py
chemsolve/utils/string_op.py
chemsolve/utils/validation.py
chemsolve/utils/vsepr.py
chemsolve/utils/warnings.py
chemsolve/utils/assets/PT_complete.csv
chemsolve/utils/assets/__init__.py
chemsolve-1.8.3.dist-info/LICENSE
chemsolve-1.8.3.dist-info/METADATA
chemsolve-1.8.3.dist-info/WHEEL
chemsolve-1.8.3.dist-info/top_level.txt
chemsolve-1.8.3.dist-info/RECORD
