Metadata-Version: 2.1
Name: chemsolve
Version: 1.8.3
Summary: A low-level chemistry library for solving and practicing chemistry problems.
Home-page: https://github.com/amogh7joshi/chemsolve
Author: Amogh Joshi
Author-email: joshi.amoghn@gmail.com
License: MIT
Platform: UNKNOWN
Classifier: Programming Language :: Python :: 3
Classifier: License :: OSI Approved :: MIT License
Classifier: Operating System :: OS Independent
